odoo/addons/mail_quoted_reply/README.rst
odoo/addons/mail_quoted_reply/__init__.py
odoo/addons/mail_quoted_reply/__manifest__.py
odoo/addons/mail_quoted_reply/i18n/ca.po
odoo/addons/mail_quoted_reply/i18n/es.po
odoo/addons/mail_quoted_reply/i18n/it.po
odoo/addons/mail_quoted_reply/i18n/mail_quoted_reply.pot
odoo/addons/mail_quoted_reply/models/__init__.py
odoo/addons/mail_quoted_reply/models/mail_compose_message.py
odoo/addons/mail_quoted_reply/models/mail_message.py
odoo/addons/mail_quoted_reply/readme/CONTRIBUTORS.md
odoo/addons/mail_quoted_reply/readme/CREDITS.md
odoo/addons/mail_quoted_reply/readme/DESCRIPTION.md
odoo/addons/mail_quoted_reply/readme/USAGE.md
odoo/addons/mail_quoted_reply/static/description/icon.png
odoo/addons/mail_quoted_reply/static/description/index.html
odoo/addons/mail_quoted_reply/static/src/message_actions.esm.js
odoo/addons/mail_quoted_reply/static/src/message_model.esm.js
odoo/addons/mail_quoted_reply/static/src/message_patch.esm.js
odoo/addons/mail_quoted_reply/tests/__init__.py
odoo/addons/mail_quoted_reply/tests/test_reply.py
odoo_addon_mail_quoted_reply-18.0.1.0.0.3.dist-info/METADATA
odoo_addon_mail_quoted_reply-18.0.1.0.0.3.dist-info/WHEEL
odoo_addon_mail_quoted_reply-18.0.1.0.0.3.dist-info/top_level.txt
odoo_addon_mail_quoted_reply-18.0.1.0.0.3.dist-info/RECORD
